evidentsource_client/__init__.py
evidentsource_client/connection.py
evidentsource_client/database.py
evidentsource_client/evident_source.py
evidentsource_client/py.typed
evidentsource_client/conversions/__init__.py
evidentsource_client/conversions/constraints.py
evidentsource_client/conversions/error.py
evidentsource_client/conversions/events.py
evidentsource_client/conversions/selectors.py
evidentsource_client/conversions/timestamps.py
evidentsource_client/proto/__init__.py
evidentsource_client/proto/cloudevents_pb2.py
evidentsource_client/proto/cloudevents_pb2.pyi
evidentsource_client/proto/cloudevents_pb2_grpc.py
evidentsource_client/proto/domain_pb2.py
evidentsource_client/proto/domain_pb2.pyi
evidentsource_client/proto/domain_pb2_grpc.py
evidentsource_client/proto/service_pb2.py
evidentsource_client/proto/service_pb2.pyi
evidentsource_client/proto/service_pb2_grpc.py
evidentsource_client-1.0.0rc1.dist-info/METADATA
evidentsource_client-1.0.0rc1.dist-info/WHEEL
evidentsource_client-1.0.0rc1.dist-info/RECORD
