Metadata-Version: 2.4
Name: evidentsource-client
Version: 1.0.0rc1
Summary: Python client for EvidentSource event sourcing database
Author-email: Evident Systems <info@evidentsystems.com>
License-Expression: MIT OR Apache-2.0
Keywords: cqrs,event-driven,eventsourcing,grpc
Classifier: Development Status :: 3 - Alpha
Classifier: Framework :: AsyncIO
Classifier: Intended Audience :: Developers
Classifier: License :: OSI Approved :: Apache Software License
Classifier: License :: OSI Approved :: MIT License
Classifier: Programming Language :: Python :: 3
Classifier: Programming Language :: Python :: 3.12
Classifier: Programming Language :: Python :: 3.13
Classifier: Typing :: Typed
Requires-Python: >=3.12
Requires-Dist: anyio>=4.0.0
Requires-Dist: evidentsource-core>=1.0.0-rc1
Requires-Dist: grpcio-tools>=1.68.0
Requires-Dist: grpcio>=1.68.0
Requires-Dist: protobuf>=5.29.0
Provides-Extra: dev
Requires-Dist: grpcio-tools>=1.68.0; extra == 'dev'
Requires-Dist: mypy>=1.13.0; extra == 'dev'
Requires-Dist: pytest-asyncio>=0.24.0; extra == 'dev'
Requires-Dist: pytest>=8.0.0; extra == 'dev'
Requires-Dist: ruff>=0.8.0; extra == 'dev'
